setup.py
wj_distribution.egg-info/PKG-INFO
wj_distribution.egg-info/SOURCES.txt
wj_distribution.egg-info/dependency_links.txt
wj_distribution.egg-info/not-zip-safe
wj_distribution.egg-info/top_level.txt
wj_probability/Binomialdistribution.py
wj_probability/Gaussiandistribution.py
wj_probability/Generaldistribution.py
wj_probability/__init__.py