Metadata-Version: 1.0
Name: wj-distribution
Version: 0.1
Summary: Gaussian and Binomial distributions
Home-page: UNKNOWN
Author: Lim Wai Jian
Author-email: jitsinkrs@hotmail.com
License: UNKNOWN
Platform: UNKNOWN
